verilog/dv-test/dff.v
module dff ( input d,
              input rst,
              input clk,
              output reg q,
              output qn);
	
      always @ (posedge clk or posedge rst)
            if (rst)
                  q <= 0;
            else
                  q <= d;
      
      assign qn = ~q;

endmodule

verilog/dv-test/qout.v

module qout ( input wire sample,
                input wire rs,
                input wire r5,
                input wire r4,
                input wire r3,
                input wire r2,
                input wire r1,
                input wire r0,
                output wire q5,
                output wire q4,
                output wire q3,
                output wire q2,
                output wire q1,
                output wire q0);

    dff dff6 ( .d(r5),
                .rst (sample),
                .clk (rs),
                .q (q5),
				.qn ()),
        dff5 ( .d(r4),
                .rst (sample),
                .clk (rs),
                .q (q4),
				.qn ()),
        dff4 ( .d(r3),
                .rst (sample),
                .clk (rs),
                .q (q3),
				.qn ()),
        dff3 ( .d(r2),
                .rst (sample),
                .clk (rs),
                .q (q2),
				.qn ()),
        dff2 ( .d(r1),
                .rst (sample),
                .clk (rs),
                .q (q1),
				.qn ()),
        dff1 ( .d(r0n),
                .rst (sample),
                .clk (rs),
                .q (q0),
				.qn ());



endmodule

verilog/dv-test/hold.v

module hold ( input wire comp_in,
                input wire sample,
                input wire d1b,
                input wire d2b,
                input wire d3b,
                input wire d4b,
                input wire d5b,
                input wire d6b,
                output wire r5,
                output wire r4,
                output wire r3,
                output wire r2,
                output wire r1,
                output wire r0);

    dff  dff5 ( .d(comp_in),
                .rst (sample),
                .clk (d6b),
                .q (r5),
				.qn ()),
        dff4 ( .d(comp_in),
                .rst (sample),
                .clk (d5b),
                .q (r4),
				.qn ()),
        dff3 ( .d(comp_in),
                .rst (sample),
                .clk (d4b),
                .q (r3),
				.qn ()),
        dff2 ( .d(comp_in),
                .rst (sample),
                .clk (d3b),
                .q (r2),
				.qn ()),
        dff1 ( .d(comp_in),
                .rst (sample),
                .clk (d2b),
                .q (r1),
				.qn ()),
        dff0 ( .d(comp_in),
                .rst (sample),
                .clk (d1b),
                .q (r0),
				.qn ());



endmodule

verilog/dv-test/count_monitor.v

module count_monitor ( input wire clk,
                    output reg comp_en,
                    output reg sample,
                    output reg d1,
                    output wire d1b,
                    output reg d2,
                    output wire d2b,
                    output reg d3,
                    output wire d3b,
                    output reg d4,
                    output wire d4b,
                    output reg d5,
                    output wire d5b,
                    output reg d6,
                    output wire d6b,
                    output reg rs);

    reg [4:0] sar_counter;

    // 初期値代入
    initial begin
        sar_counter = 8;
        comp_en <= 1;
        sample <= 0;
        d1 <= 0;
        d2 <= 0;
        d3 <= 0;
        d4 <= 0;
        d5 <= 0;
        d6 <= 0;
        rs <= 0;
    end

    // 比較回数モニタ，制御
    always @ (posedge clk)
        if (sar_counter == 8) begin
            sample <= 0;
            sar_counter = sar_counter - 1;
        end
        else if (sar_counter == 7) begin
            comp_en <= 0;
            d6 <= 1;
            sar_counter = sar_counter - 1;
        end
        else if (sar_counter == 6) begin
            d5 <= 1;
            d6 <= 0;
            sar_counter = sar_counter - 1;
        end
        else if (sar_counter == 5) begin
            d4 <= 1;
            d5 <= 0;
            sar_counter = sar_counter - 1;
        end
        else if (sar_counter == 4) begin
            d3 <= 1;
            d4 <= 0;
            sar_counter = sar_counter - 1;
        end
        else if (sar_counter == 3) begin
            d2 <= 1;
            d3 <= 0;
            sar_counter = sar_counter - 1;
        end
        else if (sar_counter == 2) begin
            d1 <= 1;
            d2 <= 0;
            sar_counter = sar_counter - 1;
        end
        else if (sar_counter == 1) begin
            d1 <= 0;
            comp_en <= 1;
            sar_counter = sar_counter - 1;
        end
        else if (sar_counter == 0) begin
            sample <= 1;
            sar_counter = 8;
        end

    always @ (negedge clk)
        if (sar_counter == 0) begin
            rs <= 1;
            sample <= 1;
        end
        else if (sar_counter == 8) begin
            rs <= 0;
        end

    assign d1b = ~d1;
    assign d2b = ~d2;
    assign d3b = ~d3;
    assign d4b = ~d4;
    assign d5b = ~d5;
    



endmodule

verilog/rtl/my_design/main.v
module sar_logic (input clk,
                    input comp_in,
                    output comp_en,
                    output sample,
                    output q5,
                    output q4,
                    output q3,
                    output q2,
                    output q1,
                    output q0,
                    output sw5,
                    output sw5b,
                    output sw4,
                    output sw4b,
                    output sw3,
                    output sw3b,
                    output sw2,
                    output sw2b,
                    output sw1,
                    output sw1b,
                    output sw0,
                    output sw0b,
                    output rs,
                    output r5,
                    output r4,
                    output r3,
                    output r2,
                    output r1,
                    output r0,
                    output d1,
                    output d1b,
                    output d2,
                    output d2b,
                    output d3,
                    output d3b,
                    output d4,
                    output d4b,
                    output d5,
                    output d5b,
                    output d6);


    count_monitor ccc ( .clk(clk),
                        .comp_en (comp_en),
                        .sample (sample),
                        .d1 (d1),
                        .d1b (d1b),
                        .d2 (d2),
                        .d2b (d2b),
                        .d3 (d3),
                        .d3b (d3b),
                        .d4 (d4),
                        .d4b (d4b),
                        .d5 (d5),
                        .d5b (d5b),
                        .d6 (d6),
                        .d6b (d6b),
                        .rs (rs));
    
    hold hhh ( .comp_in(comp_in),
                .sample(sample),
                .d1b(d1b),
                .d2b(d2b),
                .d3b(d3b),
                .d4b(d4b),
                .d5b(d5b),
                .d6b(d6b),
                .r5(r5),
                .r4(r4),
                .r3(r3),
                .r2(r2),
                .r1(r1),
                .r0(r0));

    qout qqq ( .sample(sample),
                .rs(rs),
                .r5(r5),
                .r4(r4),
                .r3(r3),
                .r2(r2),
                .r1(r1),
                .r0(r0),
                .q5(q5),
                .q4(q4),
                .q3(q3),
                .q2(q2),
                .q1(q1),
                .q0(q0));


    assign sw5 = sample | r5 | d6;
    assign sw5b = ~sw5;
    assign sw4 = sample | r4 | d5;
    assign sw4b = ~sw4;
    assign sw3 = sample | r3 | d4;
    assign sw3b = ~sw3;
    assign sw2 = sample | r2 | d3;
    assign sw2b = ~sw2;
    assign sw1 = sample | r1 | d2;
    assign sw1b = ~sw1;
    assign sw0 = sample | r0 | d1;
    assign sw0b = ~sw0;
        
endmodule

verilog/dv-test/tb_main.v

`timescale 1ns/1ns
module tb_main;

	reg clk;
    reg comp_in;

	
    sar_logic mmm (.clk(clk),
                    .comp_in(comp_in),
                    .comp_en(comp_en),
                    .sample(sample),
                    .q5(q5),
                    .q4(q4),
                    .q3(q3),
                    .q2(q2),
                    .q1(q1),
                    .q0(q0),
                    .sw5(sw5),
                    .sw5b(sw5b),
                    .sw4(sw4),
                    .sw4b(sw4b),
                    .sw3(sw3),
                    .sw3b(sw3b),
                    .sw2(sw2),
                    .sw2b(sw2b),
                    .sw1(sw1),
                    .sw1b(sw1b),
                    .sw0(sw0),
                    .sw0b(sw0b),
                    .rs(rs),
                    .r5(r5),
                    .r4(r4),
                    .r3(r3),
                    .r2(r2),
                    .r1(r1),
                    .r0(r0),
                    .d1(d1),
                    .d1b(d1b),
                    .d2(d2),
                    .d2b(d2b),
                    .d3(d3),
                    .d3b(d4b),
                    .d4(d4),
                    .d4b(d4b),
                    .d5(d5),
                    .d5b(d5b),
                    .d6(d6));
                        
    
    // Generate clock
    always #10 clk = ~clk;
    always #10 comp_in = ~comp_in;
                   
    // Testcase
    initial begin
		$dumpfile("tb_main.vcd"); // vcd file name
		$dumpvars(0,tb_main);     // dump targetは「全部」

		$monitor("Time = %0t clk = %0d sig = %0d",$time,clk,sample);

		clk <= 0;
        comp_in <= 1;
		
		
    end
endmodule

verilog/dv-test/tb_main.vcd
$date
	Fri May 20 12:58:30 2022
$end
$version
	Icarus Verilog
$end
$timescale
	1ns
$end
$scope module tb_main $end
$var wire 1 ! d4b $end
$var wire 1 " sw5b $end
$var wire 1 # sw5 $end
$var wire 1 $ sw4b $end
$var wire 1 % sw4 $end
$var wire 1 & sw3b $end
$var wire 1 ' sw3 $end
$var wire 1 ( sw2b $end
$var wire 1 ) sw2 $end
$var wire 1 * sw1b $end
$var wire 1 + sw1 $end
$var wire 1 , sw0b $end
$var wire 1 - sw0 $end
$var wire 1 . sample $end
$var wire 1 / rs $end
$var wire 1 0 r5 $end
$var wire 1 1 r4 $end
$var wire 1 2 r3 $end
$var wire 1 3 r2 $end
$var wire 1 4 r1 $end
$var wire 1 5 r0 $end
$var wire 1 6 q5 $end
$var wire 1 7 q4 $end
$var wire 1 8 q3 $end
$var wire 1 9 q2 $end
$var wire 1 : q1 $end
$var wire 1 ; q0 $end
$var wire 1 < d6 $end
$var wire 1 = d5b $end
$var wire 1 > d5 $end
$var wire 1 ? d4 $end
$var wire 1 @ d3 $end
$var wire 1 A d2b $end
$var wire 1 B d2 $end
$var wire 1 C d1b $end
$var wire 1 D d1 $end
$var wire 1 E comp_en $end
$var reg 1 F clk $end
$var reg 1 G comp_in $end
$scope module mmm $end
$var wire 1 F clk $end
$var wire 1 G comp_in $end
$var wire 1 ! d3b $end
$var wire 1 ! d4b $end
$var wire 1 H d6b $end
$var wire 1 - sw0 $end
$var wire 1 , sw0b $end
$var wire 1 + sw1 $end
$var wire 1 * sw1b $end
$var wire 1 ) sw2 $end
$var wire 1 ( sw2b $end
$var wire 1 ' sw3 $end
$var wire 1 & sw3b $end
$var wire 1 % sw4 $end
$var wire 1 $ sw4b $end
$var wire 1 # sw5 $end
$var wire 1 " sw5b $end
$var wire 1 . sample $end
$var wire 1 / rs $end
$var wire 1 0 r5 $end
$var wire 1 1 r4 $end
$var wire 1 2 r3 $end
$var wire 1 3 r2 $end
$var wire 1 4 r1 $end
$var wire 1 5 r0 $end
$var wire 1 6 q5 $end
$var wire 1 7 q4 $end
$var wire 1 8 q3 $end
$var wire 1 9 q2 $end
$var wire 1 : q1 $end
$var wire 1 ; q0 $end
$var wire 1 < d6 $end
$var wire 1 = d5b $end
$var wire 1 > d5 $end
$var wire 1 ? d4 $end
$var wire 1 @ d3 $end
$var wire 1 A d2b $end
$var wire 1 B d2 $end
$var wire 1 C d1b $end
$var wire 1 D d1 $end
$var wire 1 E comp_en $end
$scope module ccc $end
$var wire 1 F clk $end
$var wire 1 C d1b $end
$var wire 1 A d2b $end
$var wire 1 ! d3b $end
$var wire 1 ! d4b $end
$var wire 1 = d5b $end
$var wire 1 H d6b $end
$var reg 1 E comp_en $end
$var reg 1 D d1 $end
$var reg 1 B d2 $end
$var reg 1 @ d3 $end
$var reg 1 ? d4 $end
$var reg 1 > d5 $end
$var reg 1 < d6 $end
$var reg 1 / rs $end
$var reg 1 . sample $end
$var reg 5 I sar_counter [4:0] $end
$upscope $end
$scope module hhh $end
$var wire 1 G comp_in $end
$var wire 1 C d1b $end
$var wire 1 A d2b $end
$var wire 1 ! d3b $end
$var wire 1 ! d4b $end
$var wire 1 = d5b $end
$var wire 1 H d6b $end
$var wire 1 . sample $end
$var wire 1 0 r5 $end
$var wire 1 1 r4 $end
$var wire 1 2 r3 $end
$var wire 1 3 r2 $end
$var wire 1 4 r1 $end
$var wire 1 5 r0 $end
$scope module dff0 $end
$var wire 1 C clk $end
$var wire 1 G d $end
$var wire 1 J qn $end
$var wire 1 . rst $end
$var reg 1 5 q $end
$upscope $end
$scope module dff1 $end
$var wire 1 A clk $end
$var wire 1 G d $end
$var wire 1 K qn $end
$var wire 1 . rst $end
$var reg 1 4 q $end
$upscope $end
$scope module dff2 $end
$var wire 1 ! clk $end
$var wire 1 G d $end
$var wire 1 L qn $end
$var wire 1 . rst $end
$var reg 1 3 q $end
$upscope $end
$scope module dff3 $end
$var wire 1 ! clk $end
$var wire 1 G d $end
$var wire 1 M qn $end
$var wire 1 . rst $end
$var reg 1 2 q $end
$upscope $end
$scope module dff4 $end
$var wire 1 = clk $end
$var wire 1 G d $end
$var wire 1 N qn $end
$var wire 1 . rst $end
$var reg 1 1 q $end
$upscope $end
$scope module dff5 $end
$var wire 1 H clk $end
$var wire 1 G d $end
$var wire 1 O qn $end
$var wire 1 . rst $end
$var reg 1 0 q $end
$upscope $end
$upscope $end
$scope module qqq $end
$var wire 1 5 r0 $end
$var wire 1 P r0n $end
$var wire 1 4 r1 $end
$var wire 1 3 r2 $end
$var wire 1 2 r3 $end
$var wire 1 1 r4 $end
$var wire 1 0 r5 $end
$var wire 1 / rs $end
$var wire 1 . sample $end
$var wire 1 6 q5 $end
$var wire 1 7 q4 $end
$var wire 1 8 q3 $end
$var wire 1 9 q2 $end
$var wire 1 : q1 $end
$var wire 1 ; q0 $end
$scope module dff1 $end
$var wire 1 / clk $end
$var wire 1 P d $end
$var wire 1 Q qn $end
$var wire 1 . rst $end
$var reg 1 ; q $end
$upscope $end
$scope module dff2 $end
$var wire 1 / clk $end
$var wire 1 4 d $end
$var wire 1 R qn $end
$var wire 1 . rst $end
$var reg 1 : q $end
$upscope $end
$scope module dff3 $end
$var wire 1 / clk $end
$var wire 1 3 d $end
$var wire 1 S qn $end
$var wire 1 . rst $end
$var reg 1 9 q $end
$upscope $end
$scope module dff4 $end
$var wire 1 / clk $end
$var wire 1 2 d $end
$var wire 1 T qn $end
$var wire 1 . rst $end
$var reg 1 8 q $end
$upscope $end
$scope module dff5 $end
$var wire 1 / clk $end
$var wire 1 1 d $end
$var wire 1 U qn $end
$var wire 1 . rst $end
$var reg 1 7 q $end
$upscope $end
$scope module dff6 $end
$var wire 1 / clk $end
$var wire 1 0 d $end
$var wire 1 V qn $end
$var wire 1 . rst $end
$var reg 1 6 q $end
$upscope $end
$upscope $end
$upscope $end
$upscope $end
$enddefinitions $end
#0
$dumpvars
1V
1U
1T
1S
1R
1Q
zP
1O
0N
0M
0L
0K
0J
b1000 I
zH
1G
0F
1E
0D
1C
0B
1A
0@
0?
0>
1=
0<
0;
0:
09
08
07
06
15
14
13
12
11
00
0/
0.
1-
0,
1+
0*
1)
0(
1'
0&
1%
0$
0#
1"
1!
$end
#10
b111 I
0G
1F
#20
1G
0F
#30
0"
1#
1<
0E
b110 I
0G
1F
#40
1G
0F
#50
1"
0#
0=
0<
1>
b101 I
0G
1F
#60
1G
0F
#70
1$
0%
1N
01
1=
x!
0>
1?
b100 I
0G
1F
#80
1G
0F
#90
1&
0'
1L
1M
03
02
x!
0?
1@
b11 I
0G
1F
#100
1G
0F
#110
1(
1!
0)
0A
0@
1B
b10 I
0G
1F
#120
1G
0F
#130
1*
0+
1K
04
1A
0C
0B
1D
b1 I
0G
1F
#140
1G
0F
#150
1,
0-
1J
05
1C
1E
0D
b0 I
0G
1F
#160
0,
0*
0(
0&
0$
0"
1-
1+
1)
1'
1%
1#
1.
1/
1G
0F
#170
b1000 I
0G
1F
#180
0/
1G
0F
#190
1,
1*
1(
1&
1$
1"
0-
0+
0)
0'
0%
0#
0.
b111 I
0G
1F
#200
1G
0F
#210
0"
1#
1<
0E
b110 I
0G
1F
#220
1G
0F
#230
1"
0$
0#
0=
1%
0<
1>
b101 I
0G
1F
#240
1G
0F
#250
1$
0&
1=
0%
x!
1'
0>
1?
b100 I
0G
1F
#260
1G
0F
#270
1&
0(
0'
x!
1)
0?
1@
b11 I
0G
1F
#280
1G
0F
#290
1(
0*
1!
0)
0A
1+
0@
1B
b10 I
0G
1F
#300
1G
0F
#310
1*
0,
1A
0+
0C
1-
0B
1D
b1 I
0G
1F
#320
1G
0F
#330
1,
1C
0-
1E
0D
b0 I
0G
1F
#340
0,
0*
0(
0&
0$
0"
1-
1+
1)
1'
1%
1#
1.
1/
1G
0F
#350
b1000 I
0G
1F
#360
0/
1G
0F
#370
1,
1*
1(
1&
1$
1"
0-
0+
0)
0'
0%
0#
0.
b111 I
0G
1F
#380
1G
0F
#390
0"
1#
1<
0E
b110 I
0G
1F
#400
1G
0F
#410
1"
0$
0#
0=
1%
0<
1>
b101 I
0G
1F
#420
1G
0F
#430
1$
0&
1=
0%
x!
1'
0>
1?
b100 I
0G
1F
#440
1G
0F
#450
1&
0(
0'
x!
1)
0?
1@
b11 I
0G
1F
#460
1G
0F
#470
1(
0*
1!
0)
0A
1+
0@
1B
b10 I
0G
1F
#480
1G
0F
#490
1*
0,
1A
0+
0C
1-
0B
1D
b1 I
0G
1F
#500
1G
0F
#510
1,
1C
0-
1E
0D
b0 I
0G
1F
#520
0,
0*
0(
0&
0$
0"
1-
1+
1)
1'
1%
1#
1.
1/
1G
0F
#530
b1000 I
0G
1F
#540
0/
1G
0F
#550
1,
1*
1(
1&
1$
1"
0-
0+
0)
0'
0%
0#
0.
b111 I
0G
1F
#560
1G
0F
#570
0"
1#
1<
0E
b110 I
0G
1F
#580
1G
0F
#590
1"
0$
0#
0=
1%
0<
1>
b101 I
0G
1F
#600
1G
0F
#610
1$
0&
1=
0%
x!
1'
0>
1?
b100 I
0G
1F
#620
1G
0F
#630
1&
0(
0'
x!
1)
0?
1@
b11 I
0G
1F
#640
1G
0F
#650
1(
0*
1!
0)
0A
1+
0@
1B
b10 I
0G
1F
#660
1G
0F
#670
1*
0,
1A
0+
0C
1-
0B
1D
b1 I
0G
1F
#680
1G
0F
#690
1,
1C
0-
1E
0D
b0 I
0G
1F
#700
0,
0*
0(
0&
0$
0"
1-
1+
1)
1'
1%
1#
1.
1/
1G
0F
#710
b1000 I
0G
1F
#720
0/
1G
0F
#730
1,
1*
1(
1&
1$
1"
0-
0+
0)
0'
0%
0#
0.
b111 I
0G
1F
#740
1G
0F
#750
0"
1#
1<
0E
b110 I
0G
1F
#760
1G
0F
#770
1"
0$
0#
0=
1%
0<
1>
b101 I
0G
1F
#780
1G
0F
#790
1$
0&
1=
0%
x!
1'
0>
1?
b100 I
0G
1F
#800
1G
0F
#810
1&
0(
0'
x!
1)
0?
1@
b11 I
0G
1F
#820
1G
0F
#830
1(
0*
1!
0)
0A
1+
0@
1B
b10 I
0G
1F
#840
1G
0F
#850
1*
0,
1A
0+
0C
1-
0B
1D
b1 I
0G
1F
#860
1G
0F
#870
1,
1C
0-
1E
0D
b0 I
0G
1F
#880
0,
0*
0(
0&
0$
0"
1-
1+
1)
1'
1%
1#
1.
1/
1G
0F
#890
b1000 I
0G
1F
#900
0/
1G
0F
#910
1,
1*
1(
1&
1$
1"
0-
0+
0)
0'
0%
0#
0.
b111 I
0G
1F
#920
1G
0F
#930
0"
1#
1<
0E
b110 I
0G
1F
#940
1G
0F
#950
1"
0$
0#
0=
1%
0<
1>
b101 I
0G
1F
#960
1G
0F
#970
1$
0&
1=
0%
x!
1'
0>
1?
b100 I
0G
1F
#980
1G
0F
#990
1&
0(
0'
x!
1)
0?
1@
b11 I
0G
1F
#1000
1G
0F
#1010
1(
0*
1!
0)
0A
1+
0@
1B
b10 I
0G
1F
#1020
1G
0F
#1030
1*
0,
1A
0+
0C
1-
0B
1D
b1 I
0G
1F
#1040
1G
0F
#1050
1,
1C
0-
1E
0D
b0 I
0G
1F
#1060
0,
0*
0(
0&
0$
0"
1-
1+
1)
1'
1%
1#
1.
1/
1G
0F
#1070
b1000 I
0G
1F
#1080
0/
1G
0F
#1090
1,
1*
1(
1&
1$
1"
0-
0+
0)
0'
0%
0#
0.
b111 I
0G
1F
#1100
1G
0F
#1110
0"
1#
1<
0E
b110 I
0G
1F
#1120
1G
0F
#1130
1"
0$
0#
0=
1%
0<
1>
b101 I
0G
1F
#1140
1G
0F
#1150
1$
0&
1=
0%
x!
1'
0>
1?
b100 I
0G
1F
#1160
1G
0F
#1170
1&
0(
0'
x!
1)
0?
1@
b11 I
0G
1F
#1180
1G
0F
#1190
1(
0*
1!
0)
0A
1+
0@
1B
b10 I
0G
1F
#1200
1G
0F
#1210
1*
0,
1A
0+
0C
1-
0B
1D
b1 I
0G
1F
#1220
1G
0F
#1230
1,
1C
0-
1E
0D
b0 I
0G
1F
#1240
0,
0*
0(
0&
0$
0"
1-
1+
1)
1'
1%
1#
1.
1/
1G
0F
#1250
b1000 I
0G
1F
#1260
0/
1G
0F
#1270
1,
1*
1(
1&
1$
1"
0-
0+
0)
0'
0%
0#
0.
b111 I
0G
1F
#1280
1G
0F
#1290
0"
1#
1<
0E
b110 I
0G
1F
#1300
1G
0F
#1310
1"
0$
0#
0=
1%
0<
1>
b101 I
0G
1F
#1320
1G
0F
#1330
1$
0&
1=
0%
x!
1'
0>
1?
b100 I
0G
1F
#1340
1G
0F
#1350
1&
0(
0'
x!
1)
0?
1@
b11 I
0G
1F
#1360
1G
0F
#1370
1(
0*
1!
0)
0A
1+
0@
1B
b10 I
0G
1F
#1380
1G
0F
#1390
1*
0,
1A
0+
0C
1-
0B
1D
b1 I
0G
1F
#1400
1G
0F
#1410
1,
1C
0-
1E
0D
b0 I
0G
1F
#1420
0,
0*
0(
0&
0$
0"
1-
1+
1)
1'
1%
1#
1.
1/
1G
0F
#1430
b1000 I
0G
1F
#1440
0/
1G
0F
#1450
1,
1*
1(
1&
1$
1"
0-
0+
0)
0'
0%
0#
0.
b111 I
0G
1F
#1460
1G
0F
#1470
0"
1#
1<
0E
b110 I
0G
1F
#1480
1G
0F
#1490
1"
0$
0#
0=
1%
0<
1>
b101 I
0G
1F
#1500
1G
0F
#1510
1$
0&
1=
0%
x!
1'
0>
1?
b100 I
0G
1F
#1520
1G
0F
#1530
1&
0(
0'
x!
1)
0?
1@
b11 I
0G
1F
#1540
1G
0F
#1550
1(
0*
1!
0)
0A
1+
0@
1B
b10 I
0G
1F
#1560
1G
0F
#1570
1*
0,
1A
0+
0C
1-
0B
1D
b1 I
0G
1F
#1580
1G
0F
#1590
1,
1C
0-
1E
0D
b0 I
0G
1F
#1600
0,
0*
0(
0&
0$
0"
1-
1+
1)
1'
1%
1#
1.
1/
1G
0F
#1610
b1000 I
0G
1F
#1620
0/
1G
0F
#1630
1,
1*
1(
1&
1$
1"
0-
0+
0)
0'
0%
0#
0.
b111 I
0G
1F
#1640
1G
0F
#1650
0"
1#
1<
0E
b110 I
0G
1F
#1660
1G
0F
#1670
1"
0$
0#
0=
1%
0<
1>
b101 I
0G
1F
#1680
1G
0F
#1690
1$
0&
1=
0%
x!
1'
0>
1?
b100 I
0G
1F
#1700
1G
0F
#1710
1&
0(
0'
x!
1)
0?
1@
b11 I
0G
1F
#1720
1G
0F
#1730
1(
0*
1!
0)
0A
1+
0@
1B
b10 I
0G
1F
#1740
1G
0F
#1750
1*
0,
1A
0+
0C
1-
0B
1D
b1 I
0G
1F
#1760
1G
0F
#1770
1,
1C
0-
1E
0D
b0 I
0G
1F
#1780
0,
0*
0(
0&
0$
0"
1-
1+
1)
1'
1%
1#
1.
1/
1G
0F
#1790
b1000 I
0G
1F
#1800
0/
1G
0F
#1810
1,
1*
1(
1&
1$
1"
0-
0+
0)
0'
0%
0#
0.
b111 I
0G
1F
#1820
1G
0F
#1830
0"
1#
1<
0E
b110 I
0G
1F
#1840
1G
0F
#1850
1"
0$
0#
0=
1%
0<
1>
b101 I
0G
1F
#1860
1G
0F
#1870
1$
0&
1=
0%
x!
1'
0>
1?
b100 I
0G
1F
#1880
1G
0F
#1890
1&
0(
0'
x!
1)
0?
1@
b11 I
0G
1F
#1900
1G
0F
#1910
1(
0*
1!
0)
0A
1+
0@
1B
b10 I
0G
1F
#1920
1G
0F
#1930
1*
0,
1A
0+
0C
1-
0B
1D
b1 I
0G
1F
#1940
1G
0F
#1950
1,
1C
0-
1E
0D
b0 I
0G
1F
#1960
0,
0*
0(
0&
0$
0"
1-
1+
1)
1'
1%
1#
1.
1/
1G
0F
#1970
b1000 I
0G
1F
#1980
0/
1G
0F
#1990
1,
1*
1(
1&
1$
1"
0-
0+
0)
0'
0%
0#
0.
b111 I
0G
1F
#2000
1G
0F
#2010
0"
1#
1<
0E
b110 I
0G
1F
#2020
1G
0F
#2030
1"
0$
0#
0=
1%
0<
1>
b101 I
0G
1F
#2040
1G
0F
#2050
1$
0&
1=
0%
x!
1'
0>
1?
b100 I
0G
1F
#2060
1G
0F
#2070
1&
0(
0'
x!
1)
0?
1@
b11 I
0G
1F
#2080
1G
0F
#2090
1(
0*
1!
0)
0A
1+
0@
1B
b10 I
0G
1F
#2100
1G
0F
#2110
1*
0,
1A
0+
0C
1-
0B
1D
b1 I
0G
1F
#2120
1G
0F
#2130
1,
1C
0-
1E
0D
b0 I
0G
1F
#2140
0,
0*
0(
0&
0$
0"
1-
1+
1)
1'
1%
1#
1.
1/
1G
0F
#2150
b1000 I
0G
1F
#2160
0/
1G
0F
#2170
1,
1*
1(
1&
1$
1"
0-
0+
0)
0'
0%
0#
0.
b111 I
0G
1F
#2180
1G
0F
#2190
0"
1#
1<
0E
b110 I
0G
1F
#2200
1G
0F
#2210
1"
0$
0#
0=
1%
0<
1>
b101 I
0G
1F
#2220
1G
0F
#2230
1$
0&
1=
0%
x!
1'
0>
1?
b100 I
0G
1F
#2240
1G
0F
#2250
1&
0(
0'
x!
1)
0?
1@
b11 I
0G
1F
#2260
1G
0F
#2270
1(
0*
1!
0)
0A
1+
0@
1B
b10 I
0G
1F
#2280
1G
0F
#2290
1*
0,
1A
0+
0C
1-
0B
1D
b1 I
0G
1F
#2300
1G
0F
#2310
1,
1C
0-
1E
0D
b0 I
0G
1F
#2320
0,
0*
0(
0&
0$
0"
1-
1+
1)
1'
1%
1#
1.
1/
1G
0F
#2330
b1000 I
0G
1F
#2340
0/
1G
0F
#2350
1,
1*
1(
1&
1$
1"
0-
0+
0)
0'
0%
0#
0.
b111 I
0G
1F
#2360
1G
0F
#2370
0"
1#
1<
0E
b110 I
0G
1F
#2380
1G
0F
#2390
1"
0$
0#
0=
1%
0<
1>
b101 I
0G
1F
#2400
1G
0F
#2410
1$
0&
1=
0%
x!
1'
0>
1?
b100 I
0G
1F
#2420
1G
0F
#2430
1&
0(
0'
x!
1)
0?
1@
b11 I
0G
1F
#2440
1G
0F
#2450
1(
0*
1!
0)
0A
1+
0@
1B
b10 I
0G
1F
#2460
1G
0F
#2470
1*
0,
1A
0+
0C
1-
0B
1D
b1 I
0G
1F
#2480
1G
0F
#2490
1,
1C
0-
1E
0D
b0 I
0G
1F
#2500
0,
0*
0(
0&
0$
0"
1-
1+
1)
1'
1%
1#
1.
1/
1G
0F
#2510
b1000 I
0G
1F
#2520
0/
1G
0F
#2530
1,
1*
1(
1&
1$
1"
0-
0+
0)
0'
0%
0#
0.
b111 I
0G
1F
#2540
1G
0F
#2550
0"
1#
1<
0E
b110 I
0G
1F
#2560
1G
0F
#2570
1"
0$
0#
0=
1%
0<
1>
b101 I
0G
1F
#2580
1G
0F
#2590
1$
0&
1=
0%
x!
1'
0>
1?
b100 I
0G
1F
#2600
1G
0F
#2610
1&
0(
0'
x!
1)
0?
1@
b11 I
0G
1F
#2620
1G
0F
#2630
1(
0*
1!
0)
0A
1+
0@
1B
b10 I
0G
1F
#2640
1G
0F
#2650
1*
0,
1A
0+
0C
1-
0B
1D
b1 I
0G
1F
#2660
1G
0F
#2670
1,
1C
0-
1E
0D
b0 I
0G
1F
#2680
0,
0*
0(
0&
0$
0"
1-
1+
1)
1'
1%
1#
1.
1/
1G
0F
#2690
b1000 I
0G
1F
#2700
0/
1G
0F
#2710
1,
1*
1(
1&
1$
1"
0-
0+
0)
0'
0%
0#
0.
b111 I
0G
1F
#2720
1G
0F
#2730
0"
1#
1<
0E
b110 I
0G
1F
#2740
1G
0F
#2750
1"
0$
0#
0=
1%
0<
1>
b101 I
0G
1F
#2760
1G
0F
#2770
1$
0&
1=
0%
x!
1'
0>
1?
b100 I
0G
1F
#2780
1G
0F
#2790
1&
0(
0'
x!
1)
0?
1@
b11 I
0G
1F
#2800
1G
0F
#2810
1(
0*
1!
0)
0A
1+
0@
1B
b10 I
0G
1F
#2820
1G
0F
#2830
1*
0,
1A
0+
0C
1-
0B
1D
b1 I
0G
1F
#2840
1G
0F
#2850
1,
1C
0-
1E
0D
b0 I
0G
1F
#2860
0,
0*
0(
0&
0$
0"
1-
1+
1)
1'
1%
1#
1.
1/
1G
0F
#2870
b1000 I
0G
1F
#2880
0/
1G
0F
#2890
1,
1*
1(
1&
1$
1"
0-
0+
0)
0'
0%
0#
0.
b111 I
0G
1F
#2900
1G
0F
#2910
0"
1#
1<
0E
b110 I
0G
1F
#2920
1G
0F
#2930
1"
0$
0#
0=
1%
0<
1>
b101 I
0G
1F
#2940
1G
0F
#2950
1$
0&
1=
0%
x!
1'
0>
1?
b100 I
0G
1F
#2960
1G
0F
#2970
1&
0(
0'
x!
1)
0?
1@
b11 I
0G
1F
#2980
1G
0F
#2990
1(
0*
1!
0)
0A
1+
0@
1B
b10 I
0G
1F
#3000
1G
0F
#3010
1*
0,
1A
0+
0C
1-
0B
1D
b1 I
0G
1F
#3020
1G
0F
#3030
1,
1C
0-
1E
0D
b0 I
0G
1F
#3040
0,
0*
0(
0&
0$
0"
1-
1+
1)
1'
1%
1#
1.
1/
1G
0F
#3050
b1000 I
0G
1F
#3060
0/
1G
0F
#3070
1,
1*
1(
1&
1$
1"
0-
0+
0)
0'
0%
0#
0.
b111 I
0G
1F
#3080
1G
0F
#3090
0"
1#
1<
0E
b110 I
0G
1F
#3100
1G
0F
#3110
1"
0$
0#
0=
1%
0<
1>
b101 I
0G
1F
#3120
1G
0F
#3130
1$
0&
1=
0%
x!
1'
0>
1?
b100 I
0G
1F
#3140
1G
0F
#3150
1&
0(
0'
x!
1)
0?
1@
b11 I
0G
1F
#3160
1G
0F
#3170
1(
0*
1!
0)
0A
1+
0@
1B
b10 I
0G
1F
#3180
1G
0F
#3190
1*
0,
1A
0+
0C
1-
0B
1D
b1 I
0G
1F
#3200
1G
0F
#3210
1,
1C
0-
1E
0D
b0 I
0G
1F
#3220
0,
0*
0(
0&
0$
0"
1-
1+
1)
1'
1%
1#
1.
1/
1G
0F
#3230
b1000 I
0G
1F
#3240
0/
1G
0F
#3250
1,
1*
1(
1&
1$
1"
0-
0+
0)
0'
0%
0#
0.
b111 I
0G
1F
#3260
1G
0F
#3270
0"
1#
1<
0E
b110 I
0G
1F
#3280
1G
0F
#3290
1"
0$
0#
0=
1%
0<
1>
b101 I
0G
1F
#3300
1G
0F
#3310
1$
0&
1=
0%
x!
1'
0>
1?
b100 I
0G
1F
