verilog/dv-test/sample/sample.v
`timescale 1ns/1ps

module Prpg10
 #( // parameters
    parameter Prpg10_UD = 1          // Unit Delay
  )
  ( // ports
    input  wire        Clk,          // Clock
    input  wire        ResetB,       // Reset
    input  wire        PrpgUpld,     // Seed upload
    input  wire        PrpgStart,    // PRPG start
    input  wire [9:0]  PrpgSeed,     // Seed input
    output wire [9:0]  PrpgOut       // PRPG data output
  );

  reg  [9:0]  PrpgReg;
  wire [9:0]  PrpgRegIn;
  reg         PrpgStartReg;

  always @(posedge Clk, negedge ResetB) begin
    if (ResetB==1'b0) begin      // Asynronous reset
      PrpgReg      <= #Prpg10_UD 10'b00_0000_0000;
      PrpgStartReg <= #Prpg10_UD 1'b0;
    end
    else begin                   // Function
      PrpgReg      <= #Prpg10_UD PrpgRegIn;
      PrpgStartReg <= #Prpg10_UD PrpgStart;
    end
  end

  assign PrpgRegIn =
    (PrpgStartReg)? {PrpgReg[8:0],(PrpgReg[9]^PrpgReg[2])} : // x^10+ x^3 + 1
    (PrpgUpld)?      PrpgSeed :
                     PrpgReg ;

  assign PrpgOut = PrpgReg & {10{PrpgStartReg}};

endmodule

verilog/dv-test/sample/tb_sample.v
`timescale 1ns/1ps

module tb_Prpg10;
  reg        Clk, ResetB, PrpgUpld, PrpgStart;
  reg  [9:0] PrpgSeed;
  wire [9:0] PrpgOut;

  parameter CYC = 100;
  always #(CYC/2) Clk = ~Clk;

  Prpg10 dut ( // Prpg10のInstance
    .Clk (Clk),
    .ResetB (ResetB),
    .PrpgUpld (PrpgUpld),
    .PrpgStart (PrpgStart),
    .PrpgSeed (PrpgSeed),
    .PrpgOut (PrpgOut)
  );

  initial begin
    $dumpfile("tb_Prpg10.vcd"); // vcd file name
    $dumpvars(0,tb_Prpg10);     // dump targetは「全部」

    // Initilai value
    #(CYC* 0)   Clk=0; ResetB=1; PrpgUpld=0;
                PrpgStart=0; PrpgSeed=0;     // step[2]の印加値は最初から入れている
    // Reset
    #(CYC*10)   ResetB=0;                    // step[1]
    #(CYC*10)   ResetB=1;                    // step[3](step[2]は実施済み)
    // Set seed
    #(CYC*10)   PrpgSeed=10'b00_0000_0001;   // step[4]
    #(CYC*10)   PrpgUpld=1;                  // step[5]1にして
    #(CYC* 1)   PrpgUpld=0;                  // step[5]0に戻す
    // Start PRPG
    #(CYC*10)   PrpgStart=1;                 // step[6]
    // Stop PRPG after 1024 cyc
    #(CYC*1024) PrpgStart=0; // (return to start 00_0000_0001) step[7]
    // Stop simulation
    #(CYC*10)   $finish;
  end
  
endmodule

verilog/rtl/my_design/sample/tb_Prpg10.vcd
$date
	Tue May 17 21:06:17 2022
$end
$version
	Icarus Verilog
$end
$timescale
	1ps
$end
$scope module tb_Prpg10 $end
$var wire 10 ! PrpgOut [9:0] $end
$var reg 1 " Clk $end
$var reg 10 # PrpgSeed [9:0] $end
$var reg 1 $ PrpgStart $end
$var reg 1 % PrpgUpld $end
$var reg 1 & ResetB $end
$scope module dut $end
$var wire 1 " Clk $end
$var wire 10 ' PrpgOut [9:0] $end
$var wire 10 ( PrpgSeed [9:0] $end
$var wire 1 $ PrpgStart $end
$var wire 1 % PrpgUpld $end
$var wire 1 & ResetB $end
$var wire 10 ) PrpgRegIn [9:0] $end
$var reg 10 * PrpgReg [9:0] $end
$var reg 1 + PrpgStartReg $end
$upscope $end
$upscope $end
$enddefinitions $end
#0
$dumpvars
x+
bx *
bx )
b0 (
bx '
1&
0%
0$
b0 #
0"
bx !
$end
#50000
1"
#51000
b0 !
b0 '
0+
#100000
0"
#150000
1"
#200000
0"
#250000
1"
#300000
0"
#350000
1"
#400000
0"
#450000
1"
#500000
0"
#550000
1"
#600000
0"
#650000
1"
#700000
0"
#750000
1"
#800000
0"
#850000
1"
#900000
0"
#950000
1"
#1000000
0"
0&
#1001000
b0 )
b0 *
#1050000
1"
#1100000
0"
#1150000
1"
#1200000
0"
#1250000
1"
#1300000
0"
#1350000
1"
#1400000
0"
#1450000
1"
#1500000
0"
#1550000
1"
#1600000
0"
#1650000
1"
#1700000
0"
#1750000
1"
#1800000
0"
#1850000
1"
#1900000
0"
#1950000
1"
#2000000
0"
1&
#2050000
1"
#2100000
0"
#2150000
1"
#2200000
0"
#2250000
1"
#2300000
0"
#2350000
1"
#2400000
0"
#2450000
1"
#2500000
0"
#2550000
1"
#2600000
0"
#2650000
1"
#2700000
0"
#2750000
1"
#2800000
0"
#2850000
1"
#2900000
0"
#2950000
1"
#3000000
0"
b1 #
b1 (
#3050000
1"
#3100000
0"
#3150000
1"
#3200000
0"
#3250000
1"
#3300000
0"
#3350000
1"
#3400000
0"
#3450000
1"
#3500000
0"
#3550000
1"
#3600000
0"
#3650000
1"
#3700000
0"
#3750000
1"
#3800000
0"
#3850000
1"
#3900000
0"
#3950000
1"
#4000000
b1 )
0"
1%
#4050000
1"
#4051000
b1 *
#4100000
0"
0%
#4150000
1"
#4200000
0"
#4250000
1"
#4300000
0"
#4350000
1"
#4400000
0"
#4450000
1"
#4500000
0"
#4550000
1"
#4600000
0"
#4650000
1"
#4700000
0"
#4750000
1"
#4800000
0"
#4850000
1"
#4900000
0"
#4950000
1"
#5000000
0"
#5050000
1"
#5100000
0"
1$
#5150000
1"
#5151000
b10 )
b1 !
b1 '
1+
#5200000
0"
#5250000
1"
#5251000
b100 )
b10 !
b10 '
b10 *
#5300000
0"
#5350000
1"
#5351000
b1001 )
b100 !
b100 '
b100 *
#5400000
0"
#5450000
1"
#5451000
b10010 )
b1001 !
b1001 '
b1001 *
#5500000
0"
#5550000
1"
#5551000
b100100 )
b10010 !
b10010 '
b10010 *
#5600000
0"
#5650000
1"
#5651000
b1001001 )
b100100 !
b100100 '
b100100 *
#5700000
0"
#5750000
1"
#5751000
b10010010 )
b1001001 !
b1001001 '
b1001001 *
#5800000
0"
#5850000
1"
#5851000
b100100100 )
b10010010 !
b10010010 '
b10010010 *
#5900000
0"
#5950000
1"
#5951000
b1001001001 )
b100100100 !
b100100100 '
b100100100 *
#6000000
0"
#6050000
1"
#6051000
b10010011 )
b1001001001 !
b1001001001 '
b1001001001 *
#6100000
0"
#6150000
1"
#6151000
b100100110 )
b10010011 !
b10010011 '
b10010011 *
#6200000
0"
#6250000
1"
#6251000
b1001001101 )
b100100110 !
b100100110 '
b100100110 *
#6300000
0"
#6350000
1"
#6351000
b10011010 )
b1001001101 !
b1001001101 '
b1001001101 *
#6400000
0"
#6450000
1"
#6451000
b100110100 )
b10011010 !
b10011010 '
b10011010 *
#6500000
0"
#6550000
1"
#6551000
b1001101001 )
b100110100 !
b100110100 '
b100110100 *
#6600000
0"
#6650000
1"
#6651000
b11010011 )
b1001101001 !
b1001101001 '
b1001101001 *
#6700000
0"
#6750000
1"
#6751000
b110100110 )
b11010011 !
b11010011 '
b11010011 *
#6800000
0"
#6850000
1"
#6851000
b1101001101 )
b110100110 !
b110100110 '
b110100110 *
#6900000
0"
#6950000
1"
#6951000
b1010011010 )
b1101001101 !
b1101001101 '
b1101001101 *
#7000000
0"
#7050000
1"
#7051000
b100110101 )
b1010011010 !
b1010011010 '
b1010011010 *
#7100000
0"
#7150000
1"
#7151000
b1001101011 )
b100110101 !
b100110101 '
b100110101 *
#7200000
0"
#7250000
1"
#7251000
b11010111 )
b1001101011 !
b1001101011 '
b1001101011 *
#7300000
0"
#7350000
1"
#7351000
b110101111 )
b11010111 !
b11010111 '
b11010111 *
#7400000
0"
#7450000
1"
#7451000
b1101011111 )
b110101111 !
b110101111 '
b110101111 *
#7500000
0"
#7550000
1"
#7551000
b1010111110 )
b1101011111 !
b1101011111 '
b1101011111 *
#7600000
0"
#7650000
1"
#7651000
b101111100 )
b1010111110 !
b1010111110 '
b1010111110 *
#7700000
0"
#7750000
1"
#7751000
b1011111001 )
b101111100 !
b101111100 '
b101111100 *
#7800000
0"
#7850000
1"
#7851000
b111110011 )
b1011111001 !
b1011111001 '
b1011111001 *
#7900000
0"
#7950000
1"
#7951000
b1111100110 )
b111110011 !
b111110011 '
b111110011 *
#8000000
0"
#8050000
1"
#8051000
b1111001100 )
b1111100110 !
b1111100110 '
b1111100110 *
#8100000
0"
#8150000
1"
#8151000
b1110011000 )
b1111001100 !
b1111001100 '
b1111001100 *
#8200000
0"
#8250000
1"
#8251000
b1100110001 )
b1110011000 !
b1110011000 '
b1110011000 *
#8300000
0"
#8350000
1"
#8351000
b1001100011 )
b1100110001 !
b1100110001 '
b1100110001 *
#8400000
0"
#8450000
1"
#8451000
b11000111 )
b1001100011 !
b1001100011 '
b1001100011 *
#8500000
0"
#8550000
1"
#8551000
b110001111 )
b11000111 !
b11000111 '
b11000111 *
#8600000
0"
#8650000
1"
#8651000
b1100011111 )
b110001111 !
b110001111 '
b110001111 *
#8700000
0"
#8750000
1"
#8751000
b1000111110 )
b1100011111 !
b1100011111 '
b1100011111 *
#8800000
0"
#8850000
1"
#8851000
b1111100 )
b1000111110 !
b1000111110 '
b1000111110 *
#8900000
0"
#8950000
1"
#8951000
b11111001 )
b1111100 !
b1111100 '
b1111100 *
#9000000
0"
#9050000
1"
#9051000
b111110010 )
b11111001 !
b11111001 '
b11111001 *
#9100000
0"
#9150000
1"
#9151000
b1111100100 )
b111110010 !
b111110010 '
b111110010 *
#9200000
0"
#9250000
1"
#9251000
b1111001000 )
b1111100100 !
b1111100100 '
b1111100100 *
#9300000
0"
#9350000
1"
#9351000
b1110010001 )
b1111001000 !
b1111001000 '
b1111001000 *
#9400000
0"
#9450000
1"
#9451000
b1100100011 )
b1110010001 !
b1110010001 '
b1110010001 *
#9500000
0"
#9550000
1"
#9551000
b1001000111 )
b1100100011 !
b1100100011 '
b1100100011 *
#9600000
0"
#9650000
1"
#9651000
b10001110 )
b1001000111 !
b1001000111 '
b1001000111 *
#9700000
0"
#9750000
1"
#9751000
b100011101 )
b10001110 !
b10001110 '
b10001110 *
#9800000
0"
#9850000
1"
#9851000
b1000111011 )
b100011101 !
b100011101 '
b100011101 *
#9900000
0"
#9950000
1"
#9951000
b1110111 )
b1000111011 !
b1000111011 '
b1000111011 *
#10000000
0"
#10050000
1"
#10051000
b11101111 )
b1110111 !
b1110111 '
b1110111 *
#10100000
0"
#10150000
1"
#10151000
b111011111 )
b11101111 !
b11101111 '
b11101111 *
#10200000
0"
#10250000
1"
#10251000
b1110111111 )
b111011111 !
b111011111 '
b111011111 *
#10300000
0"
#10350000
1"
#10351000
b1101111110 )
b1110111111 !
b1110111111 '
b1110111111 *
#10400000
0"
#10450000
1"
#10451000
b1011111100 )
b1101111110 !
b1101111110 '
b1101111110 *
#10500000
0"
#10550000
1"
#10551000
b111111000 )
b1011111100 !
b1011111100 '
b1011111100 *
#10600000
0"
#10650000
1"
#10651000
b1111110000 )
b111111000 !
b111111000 '
b111111000 *
#10700000
0"
#10750000
1"
#10751000
b1111100001 )
b1111110000 !
b1111110000 '
b1111110000 *
#10800000
0"
#10850000
1"
#10851000
b1111000011 )
b1111100001 !
b1111100001 '
b1111100001 *
#10900000
0"
#10950000
1"
#10951000
b1110000111 )
b1111000011 !
b1111000011 '
b1111000011 *
#11000000
0"
#11050000
1"
#11051000
b1100001110 )
b1110000111 !
b1110000111 '
b1110000111 *
#11100000
0"
#11150000
1"
#11151000
b1000011100 )
b1100001110 !
b1100001110 '
b1100001110 *
#11200000
0"
#11250000
1"
#11251000
b111000 )
b1000011100 !
b1000011100 '
b1000011100 *
#11300000
0"
#11350000
1"
#11351000
b1110000 )
b111000 !
b111000 '
b111000 *
#11400000
0"
#11450000
1"
#11451000
b11100000 )
b1110000 !
b1110000 '
b1110000 *
#11500000
0"
#11550000
1"
#11551000
b111000000 )
b11100000 !
b11100000 '
b11100000 *
#11600000
0"
#11650000
1"
#11651000
b1110000000 )
b111000000 !
b111000000 '
b111000000 *
#11700000
0"
#11750000
1"
#11751000
b1100000001 )
b1110000000 !
b1110000000 '
b1110000000 *
#11800000
0"
#11850000
1"
#11851000
b1000000011 )
b1100000001 !
b1100000001 '
b1100000001 *
#11900000
0"
#11950000
1"
#11951000
b111 )
b1000000011 !
b1000000011 '
b1000000011 *
#12000000
0"
#12050000
1"
#12051000
b1111 )
b111 !
b111 '
b111 *
#12100000
0"
#12150000
1"
#12151000
b11111 )
b1111 !
b1111 '
b1111 *
#12200000
0"
#12250000
1"
#12251000
b111111 )
b11111 !
b11111 '
b11111 *
#12300000
0"
#12350000
1"
#12351000
b1111111 )
b111111 !
b111111 '
b111111 *
#12400000
0"
#12450000
1"
#12451000
b11111111 )
b1111111 !
b1111111 '
b1111111 *
#12500000
0"
#12550000
1"
#12551000
b111111111 )
b11111111 !
b11111111 '
b11111111 *
#12600000
0"
#12650000
1"
#12651000
b1111111111 )
b111111111 !
b111111111 '
b111111111 *
#12700000
0"
#12750000
1"
#12751000
b1111111110 )
b1111111111 !
b1111111111 '
b1111111111 *
#12800000
0"
#12850000
1"
#12851000
b1111111100 )
b1111111110 !
b1111111110 '
b1111111110 *
#12900000
0"
#12950000
1"
#12951000
b1111111000 )
b1111111100 !
b1111111100 '
b1111111100 *
#13000000
0"
#13050000
1"
#13051000
b1111110001 )
b1111111000 !
b1111111000 '
b1111111000 *
#13100000
0"
#13150000
1"
#13151000
b1111100011 )
b1111110001 !
b1111110001 '
b1111110001 *
#13200000
0"
#13250000
1"
#13251000
b1111000111 )
b1111100011 !
b1111100011 '
b1111100011 *
#13300000
0"
#13350000
1"
#13351000
b1110001110 )
b1111000111 !
b1111000111 '
b1111000111 *
#13400000
0"
#13450000
1"
#13451000
b1100011100 )
b1110001110 !
b1110001110 '
b1110001110 *
#13500000
0"
#13550000
1"
#13551000
b1000111000 )
b1100011100 !
b1100011100 '
b1100011100 *
#13600000
0"
#13650000
1"
#13651000
b1110001 )
b1000111000 !
b1000111000 '
b1000111000 *
#13700000
0"
#13750000
1"
#13751000
b11100010 )
b1110001 !
b1110001 '
b1110001 *
#13800000
0"
#13850000
1"
#13851000
b111000100 )
b11100010 !
b11100010 '
b11100010 *
#13900000
0"
#13950000
1"
#13951000
b1110001001 )
b111000100 !
b111000100 '
b111000100 *
#14000000
0"
#14050000
1"
#14051000
b1100010011 )
b1110001001 !
b1110001001 '
b1110001001 *
#14100000
0"
#14150000
1"
#14151000
b1000100111 )
b1100010011 !
b1100010011 '
b1100010011 *
#14200000
0"
#14250000
1"
#14251000
b1001110 )
b1000100111 !
b1000100111 '
b1000100111 *
#14300000
0"
#14350000
1"
#14351000
b10011101 )
b1001110 !
b1001110 '
b1001110 *
#14400000
0"
#14450000
1"
#14451000
b100111011 )
b10011101 !
b10011101 '
b10011101 *
#14500000
0"
#14550000
1"
#14551000
b1001110110 )
b100111011 !
b100111011 '
b100111011 *
#14600000
0"
#14650000
1"
#14651000
b11101100 )
b1001110110 !
b1001110110 '
b1001110110 *
#14700000
0"
#14750000
1"
#14751000
b111011001 )
b11101100 !
b11101100 '
b11101100 *
#14800000
0"
#14850000
1"
#14851000
b1110110010 )
b111011001 !
b111011001 '
b111011001 *
#14900000
0"
#14950000
1"
#14951000
b1101100101 )
b1110110010 !
b1110110010 '
b1110110010 *
#15000000
0"
#15050000
1"
#15051000
b1011001010 )
b1101100101 !
b1101100101 '
b1101100101 *
#15100000
0"
#15150000
1"
#15151000
b110010101 )
b1011001010 !
b1011001010 '
b1011001010 *
#15200000
0"
#15250000
1"
#15251000
b1100101011 )
b110010101 !
b110010101 '
b110010101 *
#15300000
0"
#15350000
1"
#15351000
b1001010111 )
b1100101011 !
b1100101011 '
b1100101011 *
#15400000
0"
#15450000
1"
#15451000
b10101110 )
b1001010111 !
b1001010111 '
b1001010111 *
#15500000
0"
#15550000
1"
#15551000
b101011101 )
b10101110 !
b10101110 '
b10101110 *
#15600000
0"
#15650000
1"
#15651000
b1010111011 )
b101011101 !
b101011101 '
b101011101 *
#15700000
0"
#15750000
1"
#15751000
b101110111 )
b1010111011 !
b1010111011 '
b1010111011 *
#15800000
0"
#15850000
1"
#15851000
b1011101111 )
b101110111 !
b101110111 '
b101110111 *
#15900000
0"
#15950000
1"
#15951000
b111011110 )
b1011101111 !
b1011101111 '
b1011101111 *
#16000000
0"
#16050000
1"
#16051000
b1110111101 )
b111011110 !
b111011110 '
b111011110 *
#16100000
0"
#16150000
1"
#16151000
b1101111010 )
b1110111101 !
b1110111101 '
b1110111101 *
#16200000
0"
#16250000
1"
#16251000
b1011110101 )
b1101111010 !
b1101111010 '
b1101111010 *
#16300000
0"
#16350000
1"
#16351000
b111101010 )
b1011110101 !
b1011110101 '
b1011110101 *
#16400000
0"
#16450000
1"
#16451000
b1111010100 )
b111101010 !
b111101010 '
b111101010 *
#16500000
0"
#16550000
1"
#16551000
b1110101000 )
b1111010100 !
b1111010100 '
b1111010100 *
#16600000
0"
#16650000
1"
#16651000
b1101010001 )
b1110101000 !
b1110101000 '
b1110101000 *
#16700000
0"
#16750000
1"
#16751000
b1010100011 )
b1101010001 !
b1101010001 '
b1101010001 *
#16800000
0"
#16850000
1"
#16851000
b101000111 )
b1010100011 !
b1010100011 '
b1010100011 *
#16900000
0"
#16950000
1"
#16951000
b1010001111 )
b101000111 !
b101000111 '
b101000111 *
#17000000
0"
#17050000
1"
#17051000
b100011110 )
b1010001111 !
b1010001111 '
b1010001111 *
#17100000
0"
#17150000
1"
#17151000
b1000111101 )
b100011110 !
b100011110 '
b100011110 *
#17200000
0"
#17250000
1"
#17251000
b1111010 )
b1000111101 !
b1000111101 '
b1000111101 *
#17300000
0"
#17350000
1"
#17351000
b11110100 )
b1111010 !
b1111010 '
b1111010 *
#17400000
0"
#17450000
1"
#17451000
b111101001 )
b11110100 !
b11110100 '
b11110100 *
#17500000
0"
#17550000
1"
#17551000
b1111010010 )
b111101001 !
b111101001 '
b111101001 *
#17600000
0"
#17650000
1"
#17651000
b1110100101 )
b1111010010 !
b1111010010 '
b1111010010 *
#17700000
0"
#17750000
1"
#17751000
b1101001010 )
b1110100101 !
b1110100101 '
b1110100101 *
#17800000
0"
#17850000
1"
#17851000
b1010010101 )
b1101001010 !
b1101001010 '
b1101001010 *
#17900000
0"
#17950000
1"
#17951000
b100101010 )
b1010010101 !
b1010010101 '
b1010010101 *
#18000000
0"
#18050000
1"
#18051000
b1001010100 )
b100101010 !
b100101010 '
b100101010 *
#18100000
0"
#18150000
1"
#18151000
b10101000 )
b1001010100 !
b1001010100 '
b1001010100 *
#18200000
0"
#18250000
1"
#18251000
b101010000 )
b10101000 !
b10101000 '
b10101000 *
#18300000
0"
#18350000
1"
#18351000
b1010100000 )
b101010000 !
b101010000 '
b101010000 *
#18400000
0"
#18450000
1"
#18451000
b101000001 )
b1010100000 !
b1010100000 '
b1010100000 *
#18500000
0"
#18550000
1"
#18551000
b1010000010 )
b101000001 !
b101000001 '
b101000001 *
#18600000
0"
#18650000
1"
#18651000
b100000101 )
b1010000010 !
b1010000010 '
b1010000010 *
#18700000
0"
#18750000
1"
#18751000
b1000001011 )
b100000101 !
b100000101 '
b100000101 *
#18800000
0"
#18850000
1"
#18851000
b10111 )
b1000001011 !
b1000001011 '
b1000001011 *
#18900000
0"
#18950000
1"
#18951000
b101111 )
b10111 !
b10111 '
b10111 *
#19000000
0"
#19050000
1"
#19051000
b1011111 )
b101111 !
b101111 '
b101111 *
#19100000
0"
#19150000
1"
#19151000
b10111111 )
b1011111 !
b1011111 '
b1011111 *
#19200000
0"
#19250000
1"
#19251000
b101111111 )
b10111111 !
b10111111 '
b10111111 *
#19300000
0"
#19350000
1"
#19351000
b1011111111 )
b101111111 !
b101111111 '
b101111111 *
#19400000
0"
#19450000
1"
#19451000
b111111110 )
b1011111111 !
b1011111111 '
b1011111111 *
#19500000
0"
#19550000
1"
#19551000
b1111111101 )
b111111110 !
b111111110 '
b111111110 *
#19600000
0"
#19650000
1"
#19651000
b1111111010 )
b1111111101 !
b1111111101 '
b1111111101 *
#19700000
0"
#19750000
1"
#19751000
b1111110101 )
b1111111010 !
b1111111010 '
b1111111010 *
#19800000
0"
#19850000
1"
#19851000
b1111101010 )
b1111110101 !
b1111110101 '
b1111110101 *
#19900000
0"
#19950000
1"
#19951000
b1111010101 )
b1111101010 !
b1111101010 '
b1111101010 *
#20000000
0"
#20050000
1"
#20051000
b1110101010 )
b1111010101 !
b1111010101 '
b1111010101 *
#20100000
0"
#20150000
1"
#20151000
b1101010101 )
b1110101010 !
b1110101010 '
b1110101010 *
#20200000
0"
#20250000
1"
#20251000
b1010101010 )
b1101010101 !
b1101010101 '
b1101010101 *
#20300000
0"
#20350000
1"
#20351000
b101010101 )
b1010101010 !
b1010101010 '
b1010101010 *
#20400000
0"
#20450000
1"
#20451000
b1010101011 )
b101010101 !
b101010101 '
b101010101 *
#20500000
0"
#20550000
1"
#20551000
b101010111 )
b1010101011 !
b1010101011 '
b1010101011 *
#20600000
0"
#20650000
1"
#20651000
b1010101111 )
b101010111 !
b101010111 '
b101010111 *
#20700000
0"
#20750000
1"
#20751000
b101011110 )
b1010101111 !
b1010101111 '
b1010101111 *
#20800000
0"
#20850000
1"
#20851000
b1010111101 )
b101011110 !
b101011110 '
b101011110 *
#20900000
0"
#20950000
1"
#20951000
b101111010 )
b1010111101 !
b1010111101 '
b1010111101 *
#21000000
0"
#21050000
1"
#21051000
b1011110100 )
b101111010 !
b101111010 '
b101111010 *
#21100000
0"
#21150000
1"
#21151000
b111101000 )
b1011110100 !
b1011110100 '
b1011110100 *
#21200000
0"
#21250000
1"
#21251000
b1111010000 )
b111101000 !
b111101000 '
b111101000 *
#21300000
0"
#21350000
1"
#21351000
b1110100001 )
b1111010000 !
b1111010000 '
b1111010000 *
#21400000
0"
#21450000
1"
#21451000
b1101000011 )
b1110100001 !
b1110100001 '
b1110100001 *
#21500000
0"
#21550000
1"
#21551000
b1010000111 )
b1101000011 !
b1101000011 '
b1101000011 *
#21600000
0"
#21650000
1"
#21651000
b100001110 )
b1010000111 !
b1010000111 '
b1010000111 *
#21700000
0"
#21750000
1"
#21751000
b1000011101 )
b100001110 !
b100001110 '
b100001110 *
#21800000
0"
#21850000
1"
#21851000
b111010 )
b1000011101 !
b1000011101 '
b1000011101 *
#21900000
0"
#21950000
1"
#21951000
b1110100 )
b111010 !
b111010 '
b111010 *
#22000000
0"
#22050000
1"
#22051000
b11101001 )
b1110100 !
b1110100 '
b1110100 *
#22100000
0"
#22150000
1"
#22151000
b111010010 )
b11101001 !
b11101001 '
b11101001 *
#22200000
0"
#22250000
1"
#22251000
b1110100100 )
b111010010 !
b111010010 '
b111010010 *
#22300000
0"
#22350000
1"
#22351000
b1101001000 )
b1110100100 !
b1110100100 '
b1110100100 *
#22400000
0"
#22450000
1"
#22451000
b1010010001 )
b1101001000 !
b1101001000 '
b1101001000 *
#22500000
0"
#22550000
1"
#22551000
b100100011 )
b1010010001 !
b1010010001 '
b1010010001 *
#22600000
0"
#22650000
1"
#22651000
b1001000110 )
b100100011 !
b100100011 '
b100100011 *
#22700000
0"
#22750000
1"
#22751000
b10001100 )
b1001000110 !
b1001000110 '
b1001000110 *
#22800000
0"
#22850000
1"
#22851000
b100011001 )
b10001100 !
b10001100 '
b10001100 *
#22900000
0"
#22950000
1"
#22951000
b1000110010 )
b100011001 !
b100011001 '
b100011001 *
#23000000
0"
#23050000
1"
#23051000
b1100101 )
b1000110010 !
b1000110010 '
b1000110010 *
#23100000
0"
#23150000
1"
#23151000
b11001011 )
b1100101 !
b1100101 '
b1100101 *
#23200000
0"
#23250000
1"
#23251000
b110010110 )
b11001011 !
b11001011 '
b11001011 *
#23300000
0"
#23350000
1"
#23351000
b1100101101 )
b110010110 !
b110010110 '
b110010110 *
#23400000
0"
#23450000
1"
#23451000
b1001011010 )
b1100101101 !
b1100101101 '
b1100101101 *
#23500000
0"
#23550000
1"
#23551000
b10110101 )
b1001011010 !
b1001011010 '
b1001011010 *
#23600000
0"
#23650000
1"
#23651000
b101101011 )
b10110101 !
b10110101 '
b10110101 *
#23700000
0"
#23750000
1"
#23751000
b1011010110 )
b101101011 !
b101101011 '
b101101011 *
#23800000
0"
#23850000
1"
#23851000
b110101100 )
b1011010110 !
b1011010110 '
b1011010110 *
#23900000
0"
#23950000
1"
#23951000
b1101011001 )
b110101100 !
b110101100 '
b110101100 *
#24000000
0"
#24050000
1"
#24051000
b1010110011 )
b1101011001 !
b1101011001 '
b1101011001 *
#24100000
0"
#24150000
1"
#24151000
b101100111 )
b1010110011 !
b1010110011 '
b1010110011 *
#24200000
0"
#24250000
1"
#24251000
b1011001111 )
b101100111 !
b101100111 '
b101100111 *
#24300000
0"
#24350000
1"
#24351000
b110011110 )
b1011001111 !
b1011001111 '
b1011001111 *
#24400000
0"
#24450000
1"
#24451000
b1100111101 )
b110011110 !
b110011110 '
b110011110 *
#24500000
0"
#24550000
1"
#24551000
b1001111010 )
b1100111101 !
b1100111101 '
b1100111101 *
#24600000
0"
#24650000
1"
#24651000
b11110101 )
b1001111010 !
b1001111010 '
b1001111010 *
#24700000
0"
#24750000
1"
#24751000
b111101011 )
b11110101 !
b11110101 '
b11110101 *
#24800000
0"
#24850000
1"
#24851000
b1111010110 )
b111101011 !
b111101011 '
b111101011 *
#24900000
0"
#24950000
1"
#24951000
b1110101100 )
b1111010110 !
b1111010110 '
b1111010110 *
#25000000
0"
#25050000
1"
#25051000
b1101011000 )
b1110101100 !
b1110101100 '
b1110101100 *
#25100000
0"
#25150000
1"
#25151000
b1010110001 )
b1101011000 !
b1101011000 '
b1101011000 *
#25200000
0"
#25250000
1"
#25251000
b101100011 )
b1010110001 !
b1010110001 '
b1010110001 *
#25300000
0"
#25350000
1"
#25351000
b1011000110 )
b101100011 !
b101100011 '
b101100011 *
#25400000
0"
#25450000
1"
#25451000
b110001100 )
b1011000110 !
b1011000110 '
b1011000110 *
#25500000
0"
#25550000
1"
#25551000
b1100011001 )
b110001100 !
b110001100 '
b110001100 *
#25600000
0"
#25650000
1"
#25651000
b1000110011 )
b1100011001 !
b1100011001 '
b1100011001 *
#25700000
0"
#25750000
1"
#25751000
b1100111 )
b1000110011 !
b1000110011 '
b1000110011 *
#25800000
0"
#25850000
1"
#25851000
b11001111 )
b1100111 !
b1100111 '
b1100111 *
#25900000
0"
#25950000
1"
#25951000
b110011111 )
b11001111 !
b11001111 '
b11001111 *
#26000000
0"
#26050000
1"
#26051000
b1100111111 )
b110011111 !
b110011111 '
b110011111 *
#26100000
0"
#26150000
1"
#26151000
b1001111110 )
b1100111111 !
b1100111111 '
b1100111111 *
#26200000
0"
#26250000
1"
#26251000
b11111100 )
b1001111110 !
b1001111110 '
b1001111110 *
#26300000
0"
#26350000
1"
#26351000
b111111001 )
b11111100 !
b11111100 '
b11111100 *
#26400000
0"
#26450000
1"
#26451000
b1111110010 )
b111111001 !
b111111001 '
b111111001 *
#26500000
0"
#26550000
1"
#26551000
b1111100101 )
b1111110010 !
b1111110010 '
b1111110010 *
#26600000
0"
#26650000
1"
#26651000
b1111001010 )
b1111100101 !
b1111100101 '
b1111100101 *
#26700000
0"
#26750000
1"
#26751000
b1110010101 )
b1111001010 !
b1111001010 '
b1111001010 *
#26800000
0"
#26850000
1"
#26851000
b1100101010 )
b1110010101 !
b1110010101 '
b1110010101 *
#26900000
0"
#26950000
1"
#26951000
b1001010101 )
b1100101010 !
b1100101010 '
b1100101010 *
#27000000
0"
#27050000
1"
#27051000
b10101010 )
b1001010101 !
b1001010101 '
b1001010101 *
#27100000
0"
#27150000
1"
#27151000
b101010100 )
b10101010 !
b10101010 '
b10101010 *
#27200000
0"
#27250000
1"
#27251000
b1010101001 )
b101010100 !
b101010100 '
b101010100 *
#27300000
0"
#27350000
1"
#27351000
b101010011 )
b1010101001 !
b1010101001 '
b1010101001 *
#27400000
0"
#27450000
1"
#27451000
b1010100110 )
b101010011 !
b101010011 '
b101010011 *
#27500000
0"
#27550000
1"
#27551000
b101001100 )
b1010100110 !
b1010100110 '
b1010100110 *
#27600000
0"
#27650000
1"
#27651000
b1010011001 )
b101001100 !
b101001100 '
b101001100 *
#27700000
0"
#27750000
1"
#27751000
b100110011 )
b1010011001 !
b1010011001 '
b1010011001 *
#27800000
0"
#27850000
1"
#27851000
b1001100110 )
b100110011 !
b100110011 '
b100110011 *
#27900000
0"
#27950000
1"
#27951000
b11001100 )
b1001100110 !
b1001100110 '
b1001100110 *
#28000000
0"
#28050000
1"
#28051000
b110011001 )
b11001100 !
b11001100 '
b11001100 *
#28100000
0"
#28150000
1"
#28151000
b1100110010 )
b110011001 !
b110011001 '
b110011001 *
#28200000
0"
#28250000
1"
#28251000
b1001100101 )
b1100110010 !
b1100110010 '
b1100110010 *
#28300000
0"
#28350000
1"
#28351000
b11001010 )
b1001100101 !
b1001100101 '
b1001100101 *
#28400000
0"
#28450000
1"
#28451000
b110010100 )
b11001010 !
b11001010 '
b11001010 *
#28500000
0"
#28550000
1"
#28551000
b1100101001 )
b110010100 !
b110010100 '
b110010100 *
#28600000
0"
#28650000
1"
#28651000
b1001010011 )
b1100101001 !
b1100101001 '
b1100101001 *
#28700000
0"
#28750000
1"
#28751000
b10100111 )
b1001010011 !
b1001010011 '
b1001010011 *
#28800000
0"
#28850000
1"
#28851000
b101001111 )
b10100111 !
b10100111 '
b10100111 *
#28900000
0"
#28950000
1"
#28951000
b1010011111 )
b101001111 !
b101001111 '
b101001111 *
#29000000
0"
#29050000
1"
#29051000
b100111110 )
b1010011111 !
b1010011111 '
b1010011111 *
#29100000
0"
#29150000
1"
#29151000
b1001111101 )
b100111110 !
b100111110 '
b100111110 *
#29200000
0"
#29250000
1"
#29251000
b11111010 )
b1001111101 !
b1001111101 '
b1001111101 *
#29300000
0"
#29350000
1"
#29351000
b111110100 )
b11111010 !
b11111010 '
b11111010 *
#29400000
0"
#29450000
1"
